test_repo999/__init__.py
test_repo999/py.typed
Test_Repo999-0.2.0.dist-info/LICENSE
Test_Repo999-0.2.0.dist-info/METADATA
Test_Repo999-0.2.0.dist-info/WHEEL
Test_Repo999-0.2.0.dist-info/top_level.txt
Test_Repo999-0.2.0.dist-info/RECORD
