Metadata-Version: 2.1
Name: Test-Repo999
Version: 0.2.0
Summary: Python Projects Perfected
License: GNU AFFERO GENERAL PUBLIC LICENSE
Project-URL: Documentation, https://quantized8.github.io/Test-Repo999
Project-URL: Download, https://github.com/QuanTizEd8/Test-Repo999/releases
Project-URL: Homepage, https://quantized8.github.io/Test-Repo999
Project-URL: Issue-Tracker, https://github.com/QuanTizEd8/Test-Repo999/issues
Project-URL: News, https://quantized8.github.io/Test-Repo999/news
Project-URL: Source, https://github.com/QuanTizEd8/Test-Repo999
Project-URL: Sponsor, https://quantized8.github.io/Test-Repo999/contribute/collaborate/maintain/sponsor
Keywords: development,infrastructure,streamline
Classifier: License :: OSI Approved :: GNU Affero General Public License v3 or later (AGPLv3+)
Classifier: Natural Language :: English
Classifier: Operating System :: MacOS
Classifier: Operating System :: Microsoft :: Windows
Classifier: Operating System :: POSIX :: Linux
Classifier: Programming Language :: Python :: 3 :: Only
Classifier: Programming Language :: Python :: 3.10
Classifier: Programming Language :: Python :: 3.11
Classifier: Programming Language :: Python :: 3.12
Classifier: Programming Language :: Python :: 3.9
Classifier: Typing :: Typed
Requires-Python: >=3.9
License-File: LICENSE
Requires-Dist: numpy >=1.21.2
